[
  {
    "repository_name": "Blaizzy/mlx-vlm",
    "repository_url": "https://github.com/Blaizzy/mlx-vlm"
  },
  {
    "repository_name": "badlogic/pi-mono",
    "repository_url": "https://github.com/badlogic/pi-mono"
  },
  {
    "repository_name": "block/goose",
    "repository_url": "https://github.com/block/goose"
  },
  {
    "repository_name": "dmtrKovalenko/fff.nvim",
    "repository_url": "https://github.com/dmtrKovalenko/fff.nvim"
  },
  {
    "repository_name": "freeCodeCamp/freeCodeCamp",
    "repository_url": "https://github.com/freeCodeCamp/freeCodeCamp"
  },
  {
    "repository_name": "google-ai-edge/LiteRT-LM",
    "repository_url": "https://github.com/google-ai-edge/LiteRT-LM"
  },
  {
    "repository_name": "google-ai-edge/gallery",
    "repository_url": "https://github.com/google-ai-edge/gallery"
  },
  {
    "repository_name": "onyx-dot-app/onyx",
    "repository_url": "https://github.com/onyx-dot-app/onyx"
  },
  {
    "repository_name": "siddharthvaddem/openscreen",
    "repository_url": "https://github.com/siddharthvaddem/openscreen"
  },
  {
    "repository_name": "telegramdesktop/tdesktop",
    "repository_url": "https://github.com/telegramdesktop/tdesktop"
  }
]